clifire/__init__.py
clifire/application.py
clifire/command.py
clifire/config.py
clifire/main.py
clifire/out.py
clifire/result.py
clifire/template.py
clifire/commands/__init__.py
clifire/commands/help.py
clifire/commands/version.py
clifire-0.1.11.dist-info/METADATA
clifire-0.1.11.dist-info/WHEEL
clifire-0.1.11.dist-info/entry_points.txt
clifire-0.1.11.dist-info/licenses/LICENSE
clifire-0.1.11.dist-info/RECORD
