Metadata-Version: 2.3
Name: CliFire
Version: 0.1.11
Summary: Minimal CLI framework to build Python commands quickly and elegantly.
Author-email: Roberto Lizana <rober.lizana@gmail.com>
Requires-Python: >=3.6
Requires-Dist: jinja2
Requires-Dist: pyyaml
Requires-Dist: rich
